AUTHORS.txt
LICENSE
MANIFEST.in
README.md
classifiers
requirements.txt
setup.py
background_task/__init__.py
background_task/admin.py
background_task/apps.py
background_task/exceptions.py
background_task/models.py
background_task/models_completed.py
background_task/settings.py
background_task/signals.py
background_task/tasks.py
background_task/management/__init__.py
background_task/management/commands/__init__.py
background_task/management/commands/process_tasks.py
background_task/migrations/0001_initial.py
background_task/migrations/__init__.py
background_task/tests/__init__.py
background_task/tests/test_settings.py
background_task/tests/test_settings_async.py
background_task/tests/test_tasks.py
snabb_django_background_tasks.egg-info/PKG-INFO
snabb_django_background_tasks.egg-info/SOURCES.txt
snabb_django_background_tasks.egg-info/dependency_links.txt
snabb_django_background_tasks.egg-info/requires.txt
snabb_django_background_tasks.egg-info/top_level.txt
snabb_django_background_tasks.egg-info/zip-safe